galaxy_mcp/__init__.py
galaxy_mcp/__main__.py
galaxy_mcp/server.py
galaxy_mcp-1.2.0.dist-info/licenses/LICENSE
galaxy_mcp-1.2.0.dist-info/METADATA
galaxy_mcp-1.2.0.dist-info/WHEEL
galaxy_mcp-1.2.0.dist-info/entry_points.txt
galaxy_mcp-1.2.0.dist-info/top_level.txt
galaxy_mcp-1.2.0.dist-info/RECORD
