Metadata-Version: 2.4
Name: galaxy-mcp
Version: 1.2.0
Summary: Model Context Protocol server for Galaxy bioinformatics platform
Author-email: Dannon Baker <dannon.baker@gmail.com>
Maintainer-email: Dannon Baker <dannon.baker@gmail.com>, Galaxy Project <contact@galaxyproject.org>
License-Expression: MIT
Project-URL: Homepage, https://github.com/galaxyproject/galaxy-mcp
Project-URL: Repository, https://github.com/galaxyproject/galaxy-mcp
Project-URL: Issues, https://github.com/galaxyproject/galaxy-mcp/issues
Classifier: Development Status :: 3 - Alpha
Classifier: Intended Audience :: Developers
Classifier: Programming Language :: Python :: 3
Classifier: Programming Language :: Python :: 3.10
Classifier: Programming Language :: Python :: 3.11
Classifier: Programming Language :: Python :: 3.12
Classifier: Topic :: Scientific/Engineering :: Bio-Informatics
Requires-Python: >=3.10
License-File: LICENSE
Requires-Dist: bioblend>=1.7.0
Requires-Dist: fastmcp>=2.3.0
Requires-Dist: requests>=2.32.3
Requires-Dist: python-dotenv>=1.0.0
Provides-Extra: dev
Requires-Dist: ruff>=0.11.2; extra == "dev"
Requires-Dist: mypy>=1.8.0; extra == "dev"
Requires-Dist: types-requests>=2.31.0; extra == "dev"
Requires-Dist: pytest>=8.0.0; extra == "dev"
Requires-Dist: pytest-cov>=4.1.0; extra == "dev"
Requires-Dist: pytest-asyncio>=0.25.0; extra == "dev"
Requires-Dist: pytest-watch>=4.2.0; extra == "dev"
Requires-Dist: pytest-mock>=3.14.0; extra == "dev"
Requires-Dist: responses>=0.25.0; extra == "dev"
Requires-Dist: httpx>=0.27.0; extra == "dev"
Requires-Dist: pre-commit>=3.6.0; extra == "dev"
Requires-Dist: tox>=4.11.0; extra == "dev"
Requires-Dist: build>=1.2.1; extra == "dev"
Requires-Dist: twine>=5.0.0; extra == "dev"
Dynamic: license-file
